escpos/__init__.py
escpos/capabilities.json
escpos/capabilities.py
escpos/cli.py
escpos/codepages.py
escpos/config.py
escpos/constants.py
escpos/escpos.py
escpos/exceptions.py
escpos/image.py
escpos/katakana.py
escpos/magicencode.py
escpos/printer.py
escpos/version.py
escpos/printer/__init__.py
escpos/printer/cups.py
escpos/printer/dummy.py
escpos/printer/file.py
escpos/printer/lp.py
escpos/printer/network.py
escpos/printer/serial.py
escpos/printer/usb.py
escpos/printer/win32raw.py
escpos/types/__init__.py
python_escpos-3.1.dist-info/LICENSE
python_escpos-3.1.dist-info/METADATA
python_escpos-3.1.dist-info/WHEEL
python_escpos-3.1.dist-info/entry_points.txt
python_escpos-3.1.dist-info/top_level.txt
python_escpos-3.1.dist-info/RECORD
