Metadata-Version: 2.1
Name: python-escpos
Version: 3.1
Summary: Python library to manipulate ESC/POS Printers
Home-page: https://github.com/python-escpos/python-escpos
Author: python-escpos developers
Author-email: dev@pkanzler.de
Maintainer: Patrick Kanzler
Maintainer-email: dev@pkanzler.de
License: MIT
Project-URL: Bug Tracker, https://github.com/python-escpos/python-escpos/issues
Project-URL: Documentation, https://python-escpos.readthedocs.io/en/latest/
Project-URL: Release Notes, https://github.com/python-escpos/python-escpos/releases
Keywords: ESC/POS,thermoprinter,voucher printer,printing,receipt
Platform: any
Classifier: Development Status :: 4 - Beta
Classifier: Environment :: Console
Classifier: Intended Audience :: Developers
Classifier: License :: OSI Approved :: MIT License
Classifier: Operating System :: OS Independent
Classifier: Programming Language :: Python
Classifier: Programming Language :: Python :: 3
Classifier: Programming Language :: Python :: 3.8
Classifier: Programming Language :: Python :: 3.9
Classifier: Programming Language :: Python :: 3.10
Classifier: Programming Language :: Python :: 3.11
Classifier: Programming Language :: Python :: 3.12
Classifier: Programming Language :: Python :: Implementation :: CPython
Classifier: Topic :: Software Development :: Libraries :: Python Modules
Classifier: Topic :: Office/Business :: Financial :: Point-Of-Sale
Requires-Python: >=3.8
Provides-Extra: all
Provides-Extra: cups
Provides-Extra: serial
Provides-Extra: usb
Provides-Extra: win32
License-File: LICENSE
